huobi/__init__.py
huobi/utils.py
huobi/rest/__init__.py
huobi/rest/client.py
huobi/rest/endpoint.py
huobi/rest/error.py
huobi/rest/helper.py
huobi/rest/endpoints/__init__.py
huobi/rest/endpoints/account.py
huobi/rest/endpoints/common.py
huobi/rest/endpoints/market.py
huobi/rest/endpoints/order.py
huobi/rest/endpoints/query.py
huobi/web_socket/__init__.py
huobi-0.1.12.dist-info/METADATA
huobi-0.1.12.dist-info/RECORD
huobi-0.1.12.dist-info/WHEEL
huobi-0.1.12.dist-info/top_level.txt
tests/rest/__init__.py
tests/rest/integration/__init__.py
tests/rest/integration/test_account_endpoints.py
tests/rest/integration/test_common_endpoints.py
tests/rest/integration/test_market_endpoints.py
tests/rest/integration/test_order_endpoints.py
tests/rest/integration/test_proxies.py
tests/rest/unit/__init__.py
tests/rest/unit/cases.py
tests/rest/unit/test_endpoint.py
