Metadata-Version: 2.1
Name: huobi
Version: 0.1.12
Summary: Huobi Python SDK
Home-page: https://github.com/ericls/huobi
Author: Shen Li
Author-email: dustet@gmail.com
License: MIT License
Platform: UNKNOWN
Classifier: Intended Audience :: Developers
Classifier: License :: OSI Approved :: MIT License
Classifier: Operating System :: OS Independent
Classifier: Programming Language :: Python :: 3 :: Only
Classifier: Programming Language :: Python :: 3.6
Classifier: Programming Language :: Python :: 3.7
Classifier: Topic :: Software Development :: Libraries :: Python Modules
Provides-Extra: socks
